django_skiptask/__init__.py
django_skiptask/admin.py
django_skiptask/apps.py
django_skiptask/commands.py
django_skiptask/exceptions.py
django_skiptask/handlers.py
django_skiptask/jobs.py
django_skiptask/models.py
django_skiptask/processing.py
django_skiptask/services.py
django_skiptask/tasks.py
django_skiptask/views.py
django_skiptask/worker.py
django_skiptask/management/commands/__init__.py
django_skiptask/management/commands/runworker.py
django_skiptask/management/commands/worker.py
django_skiptask/migrations/0001_initial.py
django_skiptask/migrations/__init__.py
django_skiptask-0.1.1.dist-info/licenses/LICENSE
django_skiptask-0.1.1.dist-info/METADATA
django_skiptask-0.1.1.dist-info/WHEEL
django_skiptask-0.1.1.dist-info/top_level.txt
django_skiptask-0.1.1.dist-info/RECORD
