Metadata-Version: 2.4
Name: django-skiptask
Version: 0.1.1
Summary: A Django app for database backed task queue system that uses `SKIP LOCKED`.
Author-email: Jon Huber <jon@jonhuber.com>
Project-URL: Homepage, https://github.com/jonhuber/django-skiptask
Project-URL: Repository, https://github.com/jonhuber/django-skiptask
Project-URL: Issues, https://github.com/jonhuber/django-skiptask/issues
Project-URL: Documentation, https://github.com/jonhuber/django-skiptask#readme
Project-URL: Changelog, https://github.com/jonhuber/django-skiptask/blob/main/CHANGELOG.md
Keywords: django,task-queue,background-jobs
Classifier: Development Status :: 4 - Beta
Classifier: Intended Audience :: Developers
Classifier: License :: OSI Approved :: MIT License
Classifier: Operating System :: OS Independent
Classifier: Programming Language :: Python :: 3 :: Only
Classifier: Programming Language :: Python :: 3.9
Classifier: Programming Language :: Python :: 3.10
Classifier: Programming Language :: Python :: 3.11
Classifier: Programming Language :: Python :: 3.12
Classifier: Programming Language :: Python :: 3.13
Classifier: Framework :: Django
Classifier: Framework :: Django :: 4.2
Classifier: Framework :: Django :: 5.0
Classifier: Framework :: Django :: 5.1
Classifier: Framework :: Django :: 5.2
Requires-Python: >=3.9
License-File: LICENSE
Requires-Dist: Django>=4.2
Requires-Dist: pytz
Provides-Extra: dev
Requires-Dist: pytest>=7.0; extra == "dev"
Requires-Dist: pytest-django>=4.5; extra == "dev"
Requires-Dist: black>=23.0; extra == "dev"
Requires-Dist: ipdb>=0.13; extra == "dev"
Requires-Dist: ruff>=0.1.0; extra == "dev"
Dynamic: license-file
